README.md
cbp.py
setup.py
cbp.egg-info/PKG-INFO
cbp.egg-info/SOURCES.txt
cbp.egg-info/dependency_links.txt
cbp.egg-info/entry_points.txt
cbp.egg-info/top_level.txt