Metadata-Version: 2.1
Name: cbp
Version: 1.1.1
Summary: A small CLI tool to infer the clone URL by the current path and arguments.
Home-page: https://github.com/spikespaz/clone-by-path
Author: spikespaz
Author-email: support@spikespaz.com
License: UNKNOWN
Platform: UNKNOWN
Classifier: Environment :: Console
Classifier: Intended Audience :: Developers
Classifier: License :: OSI Approved :: MIT License
Classifier: Programming Language :: Python
Classifier: Topic :: Software Development :: Version Control :: Git
Classifier: Topic :: Utilities
